__init__.py
scales_driver_async/__init__.py
scales_driver_async/connector.py
scales_driver_async/drivers.py
scales_driver_async/example.py
scales_driver_async/exeptions.py
scales_driver_async-0.0.10.dist-info/LICENSE
scales_driver_async-0.0.10.dist-info/METADATA
scales_driver_async-0.0.10.dist-info/WHEEL
scales_driver_async-0.0.10.dist-info/top_level.txt
scales_driver_async-0.0.10.dist-info/RECORD
