Metadata-Version: 2.1
Name: scales_driver_async
Version: 0.0.10
Summary: Asynchronous scale driver
Author-email: Aleksey Kravtsun <kravtsun.aleksey@gmail.com>
Project-URL: Homepage, https://github.com/kr-aleksey/ScalesDriverAsync
Project-URL: AuthorGitHub, https://github.com/kr-aleksey
Classifier: Programming Language :: Python :: 3
Classifier: License :: OSI Approved :: MIT License
Classifier: Operating System :: MacOS
Classifier: Operating System :: Microsoft :: Windows
Classifier: Operating System :: POSIX :: Linux
Classifier: Development Status :: 4 - Beta
Requires-Python: >=3.10
License-File: LICENSE
Requires-Dist: pyserial-asyncio >=0.6
